{"Maharashtra": {"Budhoda": {"Count": 1}, "Total": {"Count": 22}, "Kurhadi": {"Count": 1}, "Jawalga": {"Count": 1}, "Katpur": {"Count": 1}, "Killari": {"Count": 3}, "Killari-Karkhana": {"Count": 5}, "Koregaon": {"Count": 4}, "Karad": {"Count": 6}}, "Total": {"Count": 298}, "Gujarat": {"Gandhinagar": {"Count": 21}, "Alvakampa": {"Count": 1}, "Total": {"Count": 46}, "Dahegam": {"Count": 24}}, "Karnataka": {"Andola": {"Count": 3}, "Gowdagere": {"Count": 3}, "Pattan": {"Count": 1}, "Hitnal": {"Count": 1}, "Total": {"Count": 230}, "Madeehalli": {"Count": 52}, "Hunasagi": {"Count": 1}, "Nelogi": {"Count": 1}, "Goggi": {"Count": 2}, "Chittapur": {"Count": 5}, "Elwala": {"Count": 66}, "Jayapura": {"Count": 16}, "Tekkalakote": {"Count": 1}, "Kasaba(Holenarasipura)": {"Count": 6}, "Karur": {"Count": 1}, "Hampapura": {"Count": 6}, "Talakadu": {"Count": 15}, "Gillesugur": {"Count": 3}, "Kasaba(Kollegal)": {"Count": 1}, "Ramanathapura": {"Count": 1}, "Narona": {"Count": 1}, "Kasaba(Channarayapatna)": {"Count": 41}, "Hullahalli": {"Count": 2}, "Terakanambi": {"Count": 1}}}